promptengineers/__init__.py
promptengineers/core/__init__.py
promptengineers/core/config/__init__.py
promptengineers/core/config/functions.py
promptengineers/core/config/llm.py
promptengineers/core/config/loaders.py
promptengineers/core/config/messages.py
promptengineers/core/config/test.py
promptengineers/core/config/tools.py
promptengineers/core/exceptions/__init__.py
promptengineers/core/exceptions/messages/__init__.py
promptengineers/core/interfaces/__init__.py
promptengineers/core/interfaces/controllers/__init__.py
promptengineers/core/interfaces/repos/__init__.py
promptengineers/core/utils/__init__.py
promptengineers/core/validations/__init__.py
promptengineers/fastapi/__init__.py
promptengineers/fastapi/chat.py
promptengineers/fastapi/history.py
promptengineers/fastapi/prompt.py
promptengineers/fastapi/retrieval.py
promptengineers/fastapi/settings.py
promptengineers/fastapi/storage.py
promptengineers/fastapi/controllers/__init__.py
promptengineers/fastapi/controllers/auth.py
promptengineers/fastapi/controllers/chat.py
promptengineers/fastapi/controllers/history.py
promptengineers/fastapi/controllers/prompt.py
promptengineers/fastapi/controllers/retrieval.py
promptengineers/fastapi/controllers/settings.py
promptengineers/fastapi/controllers/storage.py
promptengineers/functions/__init__.py
promptengineers/functions/factories/__init__.py
promptengineers/llms/__init__.py
promptengineers/llms/services/__init__.py
promptengineers/llms/services/langchain/__init__.py
promptengineers/llms/services/langchain/callbacks/__init__.py
promptengineers/llms/services/langchain/chains/__init__.py
promptengineers/llms/services/openai/__init__.py
promptengineers/llms/strategies/__init__.py
promptengineers/llms/utils/__init__.py
promptengineers/models/__init__.py
promptengineers/models/loader.py
promptengineers/models/message.py
promptengineers/models/history/__init__.py
promptengineers/models/prompt/__init__.py
promptengineers/models/request/__init__.py
promptengineers-1.1.14.dist-info/METADATA
promptengineers-1.1.14.dist-info/WHEEL
promptengineers-1.1.14.dist-info/top_level.txt
promptengineers-1.1.14.dist-info/RECORD
