Metadata-Version: 2.1
Name: promptengineers
Version: 1.1.14
Summary: A collection of utilities by Prompt Engineers
Home-page: https://github.com/promptengineers-ai/core
Author: Ryan Eggleston
Author-email: kre8mymedia@gmail.com
Classifier: Programming Language :: Python :: 3
Classifier: License :: OSI Approved :: MIT License
Classifier: Operating System :: OS Independent
Requires-Dist: ujson
Provides-Extra: fastapi
Requires-Dist: fastapi ; extra == 'fastapi'
Requires-Dist: uvicorn ; extra == 'fastapi'
Requires-Dist: promptengineers[mongo] ; extra == 'fastapi'
Requires-Dist: promptengineers[storage] ; extra == 'fastapi'
Requires-Dist: promptengineers[retrieval] ; extra == 'fastapi'
Provides-Extra: llms
Requires-Dist: langchain ; extra == 'llms'
Requires-Dist: openai ; extra == 'llms'
Provides-Extra: mongo
Requires-Dist: motor ; extra == 'mongo'
Requires-Dist: pymongo ; extra == 'mongo'
Requires-Dist: cryptography ; extra == 'mongo'
Provides-Extra: prompts
Requires-Dist: promptengineers[llms] ; extra == 'prompts'
Provides-Extra: retrieval
Requires-Dist: promptengineers[llms] ; extra == 'retrieval'
Requires-Dist: redis ; extra == 'retrieval'
Requires-Dist: pinecone-client ; extra == 'retrieval'
Requires-Dist: youtube-transcript-api ; extra == 'retrieval'
Requires-Dist: pypdf ; extra == 'retrieval'
Requires-Dist: numexpr ; extra == 'retrieval'
Requires-Dist: tiktoken ; extra == 'retrieval'
Requires-Dist: nest-asyncio ; extra == 'retrieval'
Requires-Dist: beautifulsoup4 ; extra == 'retrieval'
Provides-Extra: storage
Requires-Dist: minio ; extra == 'storage'
Requires-Dist: python-multipart ; extra == 'storage'
Provides-Extra: tools
Requires-Dist: promptengineers[llms] ; extra == 'tools'
